hxlti/__init__.py
hxlti/admin.py
hxlti/apps.py
hxlti/decorators.py
hxlti/models.py
hxlti/tests.py
hxlti/urls.py
hxlti/validators.py
hxlti/views.py
hxlti/migrations/0001_initial.py
hxlti/migrations/__init__.py
hxlti_djapp-0.1.1.dist-info/METADATA
hxlti_djapp-0.1.1.dist-info/RECORD
hxlti_djapp-0.1.1.dist-info/WHEEL
hxlti_djapp-0.1.1.dist-info/top_level.txt
