Metadata-Version: 2.1
Name: hxlti-djapp
Version: 0.1.1
Summary: hx django lti provider for edx
Home-page: https://github.com/nmaekawa/hxlti-djapp
Author: nmaekawa
Author-email: nmaekawa@g.harvard.edu
License: UNKNOWN
Keywords: hx lti provider hxlti-djapp
Platform: UNKNOWN
Classifier: Development Status :: 2 - Pre-Alpha
Classifier: Intended Audience :: Developers
Classifier: Natural Language :: English
Classifier: Programming Language :: Python :: 3
Classifier: Programming Language :: Python :: 3.5
Classifier: Programming Language :: Python :: 3.6
Requires-Dist: Django
Requires-Dist: django-model-utils
Requires-Dist: pytz
Requires-Dist: lti
Requires-Dist: oauthlib
Requires-Dist: redis
